LICENSE
setup.py
lry_test/__init__.py
lry_test/lry_test.py
lry_test.egg-info/PKG-INFO
lry_test.egg-info/SOURCES.txt
lry_test.egg-info/dependency_links.txt
lry_test.egg-info/requires.txt
lry_test.egg-info/top_level.txt